AUTHORS.rst
CONTRIBUTING.rst
HISTORY.rst
LICENSE
MANIFEST.in
README.rst
setup.cfg
setup.py
docs/Makefile
docs/authors.rst
docs/conf.py
docs/contributing.rst
docs/history.rst
docs/index.rst
docs/installation.rst
docs/make.bat
docs/readme.rst
docs/usage.rst
strapi_mkdocs_plugin/__init__.py
strapi_mkdocs_plugin/cli.py
strapi_mkdocs_plugin/strapi_mkdocs_plugin.py
strapi_mkdocs_plugin.egg-info/PKG-INFO
strapi_mkdocs_plugin.egg-info/SOURCES.txt
strapi_mkdocs_plugin.egg-info/dependency_links.txt
strapi_mkdocs_plugin.egg-info/entry_points.txt
strapi_mkdocs_plugin.egg-info/not-zip-safe
strapi_mkdocs_plugin.egg-info/requires.txt
strapi_mkdocs_plugin.egg-info/top_level.txt
tests/__init__.py
tests/test_strapi_mkdocs_plugin.py